DataStats
